hydrogen_common/__init__.py
hydrogen_common/directory_paths.py
hydrogen_common/hydrogen_logging.py
hydrogen_common/job_main.py
hydrogen_common/message_bus.py
hydrogen_common/run_job.py
hydrogen_common/run_job_using_callback.py
hydrogen_common/use_message_bus.py
hydrogen_common-1.0.13.dist-info/METADATA
hydrogen_common-1.0.13.dist-info/WHEEL
hydrogen_common-1.0.13.dist-info/top_level.txt
hydrogen_common-1.0.13.dist-info/RECORD
