Metadata-Version: 2.1
Name: hydrogen-common
Version: 1.0.13
Summary: Shared common code for the hydrogen project
Home-page: https://github.com/hydroframe-ml/hydrogen-common
Author-email: wh3248@princeton.edu
License: Apache
Platform: UNKNOWN
